{
  "__inputs": [
    {
      "name": "DS_PROMETHEUS",
      "label": "prometheus",
      "description": "",
      "type": "datasource",
      "pluginId": "prometheus",
      "pluginName": "Prometheus"
    }
  ],
  "__elements": {},
  "__requires": [
    {
      "type": "grafana",
      "id": "grafana",
      "name": "Grafana",
      "version": "11.4.0"
    },
    {
      "type": "datasource",
      "id": "prometheus",
      "name": "Prometheus",
      "version": "1.0.0"
    },
    {
      "type": "panel",
      "id": "stat",
      "name": "Stat",
      "version": ""
    },
    {
      "type": "panel",
      "id": "state-timeline",
      "name": "State timeline",
      "version": ""
    },
    {
      "type": "panel",
      "id": "timeseries",
      "name": "Time series",
      "version": ""
    }
  ],
  "annotations": {
    "list": [
      {
        "builtIn": 1,
        "datasource": {
          "type": "grafana",
          "uid": "-- Grafana --"
        },
        "enable": false,
        "hide": false,
        "iconColor": "rgba(0, 211, 255, 1)",
        "name": "Annotations & Alerts",
        "target": {
          "limit": 100,
          "matchAny": false,
          "tags": [],
          "type": "dashboard"
        },
        "type": "dashboard"
      }
    ]
  },
  "editable": true,
  "fiscalYearStartMonth": 0,
  "graphTooltip": 0,
  "id": null,
  "links": [
    {
      "asDropdown": false,
      "icon": "external link",
      "includeVars": false,
      "keepTime": false,
      "tags": [],
      "targetBlank": true,
      "title": "Orange Account",
      "tooltip": "",
      "type": "link",
      "url": "https://www.orange.pl/twojekonto/"
    },
    {
      "asDropdown": false,
      "icon": "external link",
      "includeVars": false,
      "keepTime": false,
      "tags": [],
      "targetBlank": true,
      "title": "Orange Top-Up",
      "tooltip": "",
      "type": "link",
      "url": "https://doladowania.orange.pl/"
    }
  ],
  "panels": [
    {
      "datasource": {
        "type": "prometheus",
        "uid": "${datasource}"
      },
      "fieldConfig": {
        "defaults": {
          "color": {
            "mode": "thresholds"
          },
          "decimals": 2,
          "mappings": [],
          "thresholds": {
            "mode": "absolute",
            "steps": [
              {
                "color": "red",
                "value": null
              },
              {
                "color": "orange",
                "value": 1
              },
              {
                "color": "green",
                "value": 5
              }
            ]
          },
          "unit": "currencyPLN"
        },
        "overrides": []
      },
      "gridPos": {
        "h": 4,
        "w": 12,
        "x": 0,
        "y": 0
      },
      "id": 3,
      "interval": "$interval",
      "options": {
        "colorMode": "value",
        "graphMode": "none",
        "justifyMode": "auto",
        "orientation": "auto",
        "percentChangeColorMode": "standard",
        "reduceOptions": {
          "calcs": [
            "lastNotNull"
          ],
          "fields": "",
          "values": false
        },
        "showPercentChange": false,
        "textMode": "value_and_name",
        "wideLayout": true
      },
      "pluginVersion": "11.4.0",
      "targets": [
        {
          "datasource": {
            "type": "prometheus",
            "uid": "${DS_PROMETHEUS}"
          },
          "editorMode": "builder",
          "exemplar": false,
          "expr": "max by(billing_account_code) (orangepl_prepaid_cash_pln{billing_account_code=~\"$billing_account_code\", cash_type=\"gc\"})",
          "instant": false,
          "key": "Q-50df7f42-78d3-41cf-ac96-a9cffbcd0c23-0",
          "legendFormat": "{{billing_account_code}}",
          "range": true,
          "refId": "A"
        }
      ],
      "title": "Main Account Balance",
      "type": "stat"
    },
    {
      "datasource": {
        "type": "prometheus",
        "uid": "${datasource}"
      },
      "fieldConfig": {
        "defaults": {
          "color": {
            "mode": "thresholds"
          },
          "decimals": 2,
          "mappings": [],
          "thresholds": {
            "mode": "absolute",
            "steps": [
              {
                "color": "red",
                "value": null
              },
              {
                "color": "orange",
                "value": 1
              },
              {
                "color": "green",
                "value": 5
              }
            ]
          },
          "unit": "currencyPLN"
        },
        "overrides": []
      },
      "gridPos": {
        "h": 4,
        "w": 12,
        "x": 12,
        "y": 0
      },
      "id": 4,
      "interval": "$interval",
      "options": {
        "colorMode": "value",
        "graphMode": "none",
        "justifyMode": "auto",
        "orientation": "auto",
        "percentChangeColorMode": "standard",
        "reduceOptions": {
          "calcs": [
            "lastNotNull"
          ],
          "fields": "",
          "values": false
        },
        "showPercentChange": false,
        "textMode": "value_and_name",
        "wideLayout": true
      },
      "pluginVersion": "11.4.0",
      "targets": [
        {
          "datasource": {
            "type": "prometheus",
            "uid": "${DS_PROMETHEUS}"
          },
          "editorMode": "builder",
          "exemplar": false,
          "expr": "max by(billing_account_code) (orangepl_prepaid_cash_pln{billing_account_code=~\"$billing_account_code\", cash_type=\"pc\"})",
          "instant": false,
          "key": "Q-50df7f42-78d3-41cf-ac96-a9cffbcd0c23-0",
          "legendFormat": "{{billing_account_code}}",
          "range": true,
          "refId": "A"
        }
      ],
      "title": "Promotional Account Balance",
      "type": "stat"
    },
    {
      "datasource": {
        "type": "prometheus",
        "uid": "${datasource}"
      },
      "fieldConfig": {
        "defaults": {
          "color": {
            "mode": "thresholds"
          },
          "mappings": [],
          "thresholds": {
            "mode": "absolute",
            "steps": [
              {
                "color": "red",
                "value": null
              },
              {
                "color": "orange",
                "value": 1
              },
              {
                "color": "green",
                "value": 1342000000
              }
            ]
          },
          "unit": "bytes"
        },
        "overrides": []
      },
      "gridPos": {
        "h": 4,
        "w": 12,
        "x": 0,
        "y": 4
      },
      "id": 1,
      "interval": "$interval",
      "options": {
        "colorMode": "value",
        "graphMode": "none",
        "justifyMode": "auto",
        "orientation": "auto",
        "percentChangeColorMode": "standard",
        "reduceOptions": {
          "calcs": [
            "lastNotNull"
          ],
          "fields": "",
          "values": false
        },
        "showPercentChange": false,
        "textMode": "value_and_name",
        "wideLayout": true
      },
      "pluginVersion": "11.4.0",
      "targets": [
        {
          "datasource": {
            "type": "prometheus",
            "uid": "${DS_PROMETHEUS}"
          },
          "editorMode": "builder",
          "exemplar": false,
          "expr": "max by(billing_account_code) (orangepl_prepaid_allowance_data_bytes{data_type=\"DATA\", billing_account_code=~\"$billing_account_code\"})",
          "instant": false,
          "key": "Q-50df7f42-78d3-41cf-ac96-a9cffbcd0c23-0",
          "legendFormat": "{{billing_account_code}}",
          "range": true,
          "refId": "A"
        }
      ],
      "title": "Prepaid Non-Roaming Data Allowance",
      "type": "stat"
    },
    {
      "datasource": {
        "type": "prometheus",
        "uid": "${datasource}"
      },
      "fieldConfig": {
        "defaults": {
          "color": {
            "mode": "thresholds"
          },
          "mappings": [],
          "thresholds": {
            "mode": "absolute",
            "steps": [
              {
                "color": "red",
                "value": null
              },
              {
                "color": "orange",
                "value": 1
              },
              {
                "color": "green",
                "value": 1342000000
              }
            ]
          },
          "unit": "bytes"
        },
        "overrides": []
      },
      "gridPos": {
        "h": 4,
        "w": 12,
        "x": 12,
        "y": 4
      },
      "id": 2,
      "interval": "$interval",
      "options": {
        "colorMode": "value",
        "graphMode": "none",
        "justifyMode": "auto",
        "orientation": "auto",
        "percentChangeColorMode": "standard",
        "reduceOptions": {
          "calcs": [
            "lastNotNull"
          ],
          "fields": "",
          "values": false
        },
        "showPercentChange": false,
        "textMode": "value_and_name",
        "wideLayout": true
      },
      "pluginVersion": "11.4.0",
      "targets": [
        {
          "datasource": {
            "type": "prometheus",
            "uid": "${DS_PROMETHEUS}"
          },
          "editorMode": "builder",
          "exemplar": false,
          "expr": "max by(billing_account_code) (orangepl_prepaid_allowance_data_bytes{data_type=\"DATA_R\", billing_account_code=~\"$billing_account_code\"})",
          "instant": false,
          "key": "Q-50df7f42-78d3-41cf-ac96-a9cffbcd0c23-0",
          "legendFormat": "{{billing_account_code}}",
          "range": true,
          "refId": "A"
        }
      ],
      "title": "Prepaid Roaming Data Allowance",
      "type": "stat"
    },
    {
      "datasource": {
        "type": "prometheus",
        "uid": "${datasource}"
      },
      "fieldConfig": {
        "defaults": {
          "color": {
            "mode": "thresholds"
          },
          "mappings": [],
          "thresholds": {
            "mode": "absolute",
            "steps": [
              {
                "color": "text",
                "value": null
              }
            ]
          },
          "unit": "dateTimeFromNow"
        },
        "overrides": []
      },
      "gridPos": {
        "h": 4,
        "w": 24,
        "x": 0,
        "y": 8
      },
      "id": 9,
      "interval": "$interval",
      "options": {
        "colorMode": "value",
        "graphMode": "none",
        "justifyMode": "auto",
        "orientation": "vertical",
        "percentChangeColorMode": "standard",
        "reduceOptions": {
          "calcs": [
            "lastNotNull"
          ],
          "fields": "",
          "values": false
        },
        "showPercentChange": false,
        "text": {
          "valueSize": 20
        },
        "textMode": "value_and_name",
        "wideLayout": false
      },
      "pluginVersion": "11.4.0",
      "targets": [
        {
          "datasource": {
            "type": "prometheus",
            "uid": "${DS_PROMETHEUS}"
          },
          "disableTextWrap": false,
          "editorMode": "builder",
          "exemplar": false,
          "expr": "sum by(billing_account_code, description) (orangepl_prepaid_allowance_data_item_expiry_date{data_type=\"DATA\", billing_account_code=~\"$billing_account_code\"} * 1000)",
          "fullMetaSearch": false,
          "includeNullMetadata": true,
          "instant": false,
          "key": "Q-50df7f42-78d3-41cf-ac96-a9cffbcd0c23-0",
          "legendFormat": "{{billing_account_code}} ({{description}})",
          "range": true,
          "refId": "A",
          "useBackend": false
        }
      ],
      "title": "Allowance Expiration Dates",
      "transformations": [
        {
          "disabled": true,
          "id": "reduce",
          "options": {
            "includeTimeField": false,
            "labelsToFields": false,
            "mode": "seriesToRows",
            "reducers": [
              "lastNotNull"
            ]
          }
        },
        {
          "disabled": true,
          "id": "sortBy",
          "options": {
            "fields": {},
            "sort": [
              {
                "desc": false,
                "field": "Last *"
              }
            ]
          }
        },
        {
          "disabled": true,
          "id": "rowsToFields",
          "options": {}
        }
      ],
      "type": "stat"
    },
    {
      "datasource": {
        "type": "prometheus",
        "uid": "${datasource}"
      },
      "fieldConfig": {
        "defaults": {
          "color": {
            "mode": "palette-classic"
          },
          "custom": {
            "axisBorderShow": false,
            "axisCenteredZero": false,
            "axisColorMode": "text",
            "axisLabel": "",
            "axisPlacement": "auto",
            "barAlignment": 0,
            "barWidthFactor": 0.6,
            "drawStyle": "line",
            "fillOpacity": 0,
            "gradientMode": "none",
            "hideFrom": {
              "legend": false,
              "tooltip": false,
              "viz": false
            },
            "insertNulls": false,
            "lineInterpolation": "linear",
            "lineWidth": 1,
            "pointSize": 5,
            "scaleDistribution": {
              "type": "linear"
            },
            "showPoints": "never",
            "spanNulls": false,
            "stacking": {
              "group": "A",
              "mode": "none"
            },
            "thresholdsStyle": {
              "mode": "off"
            }
          },
          "mappings": [],
          "thresholds": {
            "mode": "absolute",
            "steps": [
              {
                "color": "red",
                "value": null
              },
              {
                "color": "orange",
                "value": 1
              },
              {
                "color": "green",
                "value": 1342000000
              }
            ]
          },
          "unit": "bytes"
        },
        "overrides": []
      },
      "gridPos": {
        "h": 10,
        "w": 24,
        "x": 0,
        "y": 12
      },
      "id": 5,
      "interval": "$interval",
      "options": {
        "legend": {
          "calcs": [
            "firstNotNull",
            "lastNotNull",
            "range",
            "diff"
          ],
          "displayMode": "table",
          "placement": "bottom",
          "showLegend": true
        },
        "tooltip": {
          "mode": "multi",
          "sort": "none"
        }
      },
      "pluginVersion": "11.4.0",
      "targets": [
        {
          "datasource": {
            "type": "prometheus",
            "uid": "${DS_PROMETHEUS}"
          },
          "editorMode": "builder",
          "exemplar": false,
          "expr": "max by(billing_account_code) (orangepl_prepaid_allowance_data_bytes{data_type=\"DATA\", billing_account_code=~\"$billing_account_code\"})",
          "instant": false,
          "key": "Q-50df7f42-78d3-41cf-ac96-a9cffbcd0c23-0",
          "legendFormat": "{{billing_account_code}}",
          "range": true,
          "refId": "A"
        }
      ],
      "title": "Prepaid Non-Roaming Data Allowance Remaining",
      "type": "timeseries"
    },
    {
      "datasource": {
        "type": "prometheus",
        "uid": "${datasource}"
      },
      "fieldConfig": {
        "defaults": {
          "color": {
            "mode": "palette-classic"
          },
          "custom": {
            "axisBorderShow": false,
            "axisCenteredZero": false,
            "axisColorMode": "text",
            "axisLabel": "",
            "axisPlacement": "auto",
            "barAlignment": 0,
            "barWidthFactor": 0.6,
            "drawStyle": "line",
            "fillOpacity": 0,
            "gradientMode": "none",
            "hideFrom": {
              "legend": false,
              "tooltip": false,
              "viz": false
            },
            "insertNulls": false,
            "lineInterpolation": "linear",
            "lineWidth": 1,
            "pointSize": 5,
            "scaleDistribution": {
              "type": "linear"
            },
            "showPoints": "never",
            "spanNulls": false,
            "stacking": {
              "group": "A",
              "mode": "none"
            },
            "thresholdsStyle": {
              "mode": "off"
            }
          },
          "mappings": [],
          "thresholds": {
            "mode": "absolute",
            "steps": [
              {
                "color": "red",
                "value": null
              },
              {
                "color": "orange",
                "value": 1
              },
              {
                "color": "green",
                "value": 1342000000
              }
            ]
          },
          "unit": "bytes"
        },
        "overrides": []
      },
      "gridPos": {
        "h": 10,
        "w": 24,
        "x": 0,
        "y": 22
      },
      "id": 8,
      "interval": "$interval",
      "options": {
        "legend": {
          "calcs": [
            "firstNotNull",
            "lastNotNull",
            "range",
            "diff"
          ],
          "displayMode": "table",
          "placement": "bottom",
          "showLegend": true
        },
        "tooltip": {
          "mode": "multi",
          "sort": "none"
        }
      },
      "pluginVersion": "11.4.0",
      "targets": [
        {
          "datasource": {
            "type": "prometheus",
            "uid": "${DS_PROMETHEUS}"
          },
          "disableTextWrap": false,
          "editorMode": "builder",
          "exemplar": false,
          "expr": "max by(billing_account_code) (orangepl_prepaid_allowance_data_bytes{data_type=\"DATA_R\", billing_account_code=~\"$billing_account_code\"})",
          "fullMetaSearch": false,
          "includeNullMetadata": true,
          "instant": false,
          "key": "Q-50df7f42-78d3-41cf-ac96-a9cffbcd0c23-0",
          "legendFormat": "{{billing_account_code}}",
          "range": true,
          "refId": "A",
          "useBackend": false
        }
      ],
      "title": "Prepaid Roaming Data Allowance Remaining",
      "type": "timeseries"
    },
    {
      "datasource": {
        "type": "prometheus",
        "uid": "${datasource}"
      },
      "fieldConfig": {
        "defaults": {
          "color": {
            "mode": "palette-classic"
          },
          "custom": {
            "axisBorderShow": false,
            "axisCenteredZero": false,
            "axisColorMode": "text",
            "axisLabel": "",
            "axisPlacement": "auto",
            "barAlignment": 0,
            "barWidthFactor": 0.6,
            "drawStyle": "bars",
            "fillOpacity": 100,
            "gradientMode": "none",
            "hideFrom": {
              "legend": false,
              "tooltip": false,
              "viz": false
            },
            "insertNulls": false,
            "lineInterpolation": "linear",
            "lineWidth": 1,
            "pointSize": 5,
            "scaleDistribution": {
              "type": "linear"
            },
            "showPoints": "never",
            "spanNulls": false,
            "stacking": {
              "group": "A",
              "mode": "none"
            },
            "thresholdsStyle": {
              "mode": "off"
            }
          },
          "mappings": [],
          "thresholds": {
            "mode": "absolute",
            "steps": [
              {
                "color": "red",
                "value": null
              },
              {
                "color": "orange",
                "value": 1
              },
              {
                "color": "green",
                "value": 1342000000
              }
            ]
          },
          "unit": "bytes"
        },
        "overrides": []
      },
      "gridPos": {
        "h": 11,
        "w": 24,
        "x": 0,
        "y": 32
      },
      "id": 6,
      "interval": "$interval",
      "options": {
        "legend": {
          "calcs": [
            "firstNotNull",
            "lastNotNull",
            "sum",
            "diff"
          ],
          "displayMode": "table",
          "placement": "bottom",
          "showLegend": true
        },
        "tooltip": {
          "mode": "multi",
          "sort": "none"
        }
      },
      "pluginVersion": "11.4.0",
      "targets": [
        {
          "datasource": {
            "type": "prometheus",
            "uid": "${DS_PROMETHEUS}"
          },
          "disableTextWrap": false,
          "editorMode": "builder",
          "exemplar": false,
          "expr": "max by(billing_account_code) (delta(orangepl_prepaid_allowance_data_bytes{data_type=\"DATA\", billing_account_code=~\"$billing_account_code\"}[$__interval]))",
          "fullMetaSearch": false,
          "includeNullMetadata": true,
          "instant": false,
          "key": "Q-50df7f42-78d3-41cf-ac96-a9cffbcd0c23-0",
          "legendFormat": "{{billing_account_code}}",
          "range": true,
          "refId": "A",
          "useBackend": false
        }
      ],
      "title": "Prepaid Non-Roaming Data Allowance Changes",
      "type": "timeseries"
    },
    {
      "datasource": {
        "type": "prometheus",
        "uid": "${datasource}"
      },
      "fieldConfig": {
        "defaults": {
          "color": {
            "mode": "palette-classic"
          },
          "custom": {
            "axisBorderShow": false,
            "axisCenteredZero": false,
            "axisColorMode": "text",
            "axisLabel": "",
            "axisPlacement": "auto",
            "barAlignment": 0,
            "barWidthFactor": 0.6,
            "drawStyle": "bars",
            "fillOpacity": 100,
            "gradientMode": "none",
            "hideFrom": {
              "legend": false,
              "tooltip": false,
              "viz": false
            },
            "insertNulls": false,
            "lineInterpolation": "linear",
            "lineWidth": 1,
            "pointSize": 5,
            "scaleDistribution": {
              "type": "linear"
            },
            "showPoints": "never",
            "spanNulls": false,
            "stacking": {
              "group": "A",
              "mode": "none"
            },
            "thresholdsStyle": {
              "mode": "off"
            }
          },
          "mappings": [],
          "thresholds": {
            "mode": "absolute",
            "steps": [
              {
                "color": "red",
                "value": null
              },
              {
                "color": "orange",
                "value": 1
              },
              {
                "color": "green",
                "value": 1342000000
              }
            ]
          },
          "unit": "bytes"
        },
        "overrides": []
      },
      "gridPos": {
        "h": 11,
        "w": 24,
        "x": 0,
        "y": 43
      },
      "id": 7,
      "interval": "$interval",
      "options": {
        "legend": {
          "calcs": [
            "firstNotNull",
            "lastNotNull",
            "sum",
            "diff"
          ],
          "displayMode": "table",
          "placement": "bottom",
          "showLegend": true
        },
        "tooltip": {
          "mode": "multi",
          "sort": "none"
        }
      },
      "pluginVersion": "11.4.0",
      "targets": [
        {
          "datasource": {
            "type": "prometheus",
            "uid": "${DS_PROMETHEUS}"
          },
          "disableTextWrap": false,
          "editorMode": "code",
          "exemplar": false,
          "expr": "(max by(billing_account_code) (delta(orangepl_prepaid_allowance_data_bytes{data_type=\"DATA\", billing_account_code=~\"$billing_account_code\"}[$__interval])) < 0) * -1",
          "fullMetaSearch": false,
          "includeNullMetadata": true,
          "instant": false,
          "key": "Q-50df7f42-78d3-41cf-ac96-a9cffbcd0c23-0",
          "legendFormat": "{{billing_account_code}}",
          "range": true,
          "refId": "A",
          "useBackend": false
        }
      ],
      "title": "Prepaid Non-Roaming Data Allowance Consumption",
      "type": "timeseries"
    },
    {
      "datasource": {
        "type": "prometheus",
        "uid": "${datasource}"
      },
      "fieldConfig": {
        "defaults": {
          "color": {
            "fixedColor": "text",
            "mode": "continuous-RdYlGr"
          },
          "custom": {
            "fillOpacity": 70,
            "hideFrom": {
              "legend": false,
              "tooltip": false,
              "viz": false
            },
            "insertNulls": false,
            "lineWidth": 0,
            "spanNulls": 604800000
          },
          "mappings": [],
          "thresholds": {
            "mode": "absolute",
            "steps": [
              {
                "color": "text",
                "value": null
              }
            ]
          },
          "unit": "dateTimeAsLocal"
        },
        "overrides": []
      },
      "gridPos": {
        "h": 9,
        "w": 24,
        "x": 0,
        "y": 54
      },
      "id": 10,
      "interval": "$interval",
      "options": {
        "alignValue": "center",
        "legend": {
          "displayMode": "list",
          "placement": "bottom",
          "showLegend": false
        },
        "mergeValues": true,
        "perPage": 5,
        "rowHeight": 0.9,
        "showValue": "always",
        "tooltip": {
          "mode": "single",
          "sort": "none"
        }
      },
      "pluginVersion": "11.4.0",
      "targets": [
        {
          "datasource": {
            "type": "prometheus",
            "uid": "${DS_PROMETHEUS}"
          },
          "disableTextWrap": false,
          "editorMode": "builder",
          "exemplar": false,
          "expr": "sum by(billing_account_code, description) (orangepl_prepaid_allowance_data_item_expiry_date{data_type=\"DATA\", billing_account_code=~\"$billing_account_code\"}) * 1000",
          "fullMetaSearch": false,
          "includeNullMetadata": true,
          "instant": false,
          "key": "Q-50df7f42-78d3-41cf-ac96-a9cffbcd0c23-0",
          "legendFormat": "{{billing_account_code}} ({{description}})",
          "range": true,
          "refId": "A",
          "useBackend": false
        }
      ],
      "title": "Allowance Expiration Date Timeline",
      "transformations": [
        {
          "disabled": true,
          "id": "reduce",
          "options": {
            "includeTimeField": false,
            "labelsToFields": false,
            "mode": "seriesToRows",
            "reducers": [
              "lastNotNull"
            ]
          }
        },
        {
          "disabled": true,
          "id": "sortBy",
          "options": {
            "fields": {},
            "sort": [
              {
                "desc": false,
                "field": "Last *"
              }
            ]
          }
        },
        {
          "disabled": true,
          "id": "rowsToFields",
          "options": {}
        }
      ],
      "type": "state-timeline"
    }
  ],
  "refresh": "",
  "schemaVersion": 40,
  "tags": [
    "4g",
    "lte",
    "orange.pl",
    "mobile data",
    "5g",
    "prepaid"
  ],
  "templating": {
    "list": [
      {
        "current": {},
        "includeAll": false,
        "label": "Data Source",
        "name": "datasource",
        "options": [],
        "query": "prometheus",
        "refresh": 1,
        "regex": "",
        "type": "datasource"
      },
      {
        "current": {},
        "datasource": {
          "type": "prometheus",
          "uid": "${datasource}"
        },
        "definition": "label_values(orangepl_billing_accounts_info,billing_account_code)",
        "includeAll": true,
        "label": "Phone Number",
        "multi": true,
        "name": "billing_account_code",
        "options": [],
        "query": {
          "query": "label_values(orangepl_billing_accounts_info,billing_account_code)",
          "refId": "PrometheusVariableQueryEditor-VariableQuery"
        },
        "refresh": 1,
        "regex": "",
        "sort": 3,
        "type": "query"
      },
      {
        "auto": false,
        "auto_count": 30,
        "auto_min": "10s",
        "current": {
          "text": "1h",
          "value": "1h"
        },
        "label": "Interval",
        "name": "interval",
        "options": [
          {
            "selected": true,
            "text": "1h",
            "value": "1h"
          },
          {
            "selected": false,
            "text": "6h",
            "value": "6h"
          },
          {
            "selected": false,
            "text": "12h",
            "value": "12h"
          },
          {
            "selected": false,
            "text": "1d",
            "value": "1d"
          },
          {
            "selected": false,
            "text": "7d",
            "value": "7d"
          },
          {
            "selected": false,
            "text": "14d",
            "value": "14d"
          },
          {
            "selected": false,
            "text": "30d",
            "value": "30d"
          }
        ],
        "query": "1h,6h,12h,1d,7d,14d,30d",
        "refresh": 2,
        "type": "interval"
      }
    ]
  },
  "time": {
    "from": "now-2d",
    "to": "now"
  },
  "timepicker": {},
  "timezone": "",
  "title": "Orange Prepaid Poland",
  "uid": "dccc25ff-d54f-4c85-b355-d96eebd04270",
  "version": 37,
  "weekStart": ""
}